historical_data_migration/__init__.py
historical_data_migration/migration.py
webengage_migration-0.1.1.dist-info/METADATA
webengage_migration-0.1.1.dist-info/WHEEL
webengage_migration-0.1.1.dist-info/entry_points.txt
webengage_migration-0.1.1.dist-info/top_level.txt
webengage_migration-0.1.1.dist-info/RECORD
